spMariaDbConnectorPy/MariaDbConnector.py
spMariaDbConnectorPy/__init__.py
spmariadbconnectorpy-1.0.2.dist-info/METADATA
spmariadbconnectorpy-1.0.2.dist-info/WHEEL
spmariadbconnectorpy-1.0.2.dist-info/licenses/LICENSE
spmariadbconnectorpy-1.0.2.dist-info/RECORD
