Metadata-Version: 2.4
Name: spMariaDbConnectorPy
Version: 1.0.2
Summary: A Python package for simplifying coding and handling data with the MariaDB module.
Project-URL: Homepage, https://github.com/krokoreit/spMariaDbConnectorPy
Project-URL: Source Code, https://github.com/krokoreit/spMariaDbConnectorPy
Author-email: krokoreit <krokoreit@gmail.com>
License-Expression: MIT
License-File: LICENSE
Keywords: MariaDB,MySQL,auto-commit,database,query
Classifier: Operating System :: OS Independent
Classifier: Programming Language :: Python :: 3
Requires-Python: >=3.10
Requires-Dist: mariadb
